graphpy_example_package/__init__.py
graphpy_example_package/create_graph.py
graphpy_example_package/gatconv.py
graphpy_example_package/gcnconv.py
graphpy_example_package/ginconv.py
graphpy_example_package/gp_apis.py
graphpy_example_package/gp_apis_big.py
graphpy_example_package/gp_apis_tf.py
graphpy_example_package/kernel.cpython-38-x86_64-linux-gnu.so
graphpy_example_package/pubmed_util.py
graphpy_example_package/pygraph.cpython-38-x86_64-linux-gnu.so
graphpy_example_package/save_graph.py
graphpy_example_package/save_graph_noeid.py
graphpy_example_package/sparse.py
graphpy_example_package/sparse_tf.py
graphpy_example_package/utils.py
graphpy_example_package-0.0.6.dist-info/METADATA
graphpy_example_package-0.0.6.dist-info/WHEEL
graphpy_example_package-0.0.6.dist-info/licenses/LICENSE
graphpy_example_package-0.0.6.dist-info/RECORD
