Metadata-Version: 2.1
Name: graphpy_example_package
Version: 0.0.6
Summary: A small example package
Project-URL: Homepage, https://github.com/Ed-gong/GraphPy_workflow
Project-URL: Bug Tracker, https://github.com/Ed-gong/GraphPy_workflow/issues
Author-email: Example Author <author@example.com>
License-File: LICENSE
Classifier: License :: OSI Approved :: MIT License
Classifier: Operating System :: OS Independent
Classifier: Programming Language :: Python :: 3
Requires-Python: >=3.7
